
- The association between a nonstatic member class instance and its enclosing instance is established when the member class instance is created and cannot be modified thereafter

non-static member classì˜ ì¸ìŠ¤í„´ìŠ¤ëŠ” ìƒì„±ë  ë•Œ ì™¸ë¶€ í´ë˜ìŠ¤ ì¸ìŠ¤í„´ìŠ¤ì™€ì˜ ì—°ê²°(association)ì´ ë§Œë“¤ì–´ì§

 ì°¸ì¡° ê´€ê³„ëŠ” ìƒì„± ì‹œì ì— ê³ ì •ë˜ê³ , ì´í›„ì— ë‹¤ë¥¸ ì™¸ë¶€ ì¸ìŠ¤í„´ìŠ¤ë¡œ ë°”ê¿€ ìˆ˜ ì—†ìŠµë‹ˆë‹¤.
    
```java
class Outer {
    class Inner {
        void hello() {
            System.out.println("Hello from inner, outer hash = " + Outer.this.hashCode());
        }
    }
}

Outer a = new Outer();
Outer b = new Outer();

Outer.Inner inner = a.new Inner();  // aì™€ ì—°ê²°ë¨
// inner = b.new Inner();  âŒ ê¸°ì¡´ innerì˜ ì—°ê²°ì„ bë¡œ ë°”ê¿€ ìˆ˜ ì—†ìŒ
```

---

Normally, the association is established automatically by invoking a nonstatic member class constructor from within an instance method of the enclosing class.

ì¼ë°˜ì ìœ¼ë¡œ ì´ ì—°ê²°ì€ ì™¸ë¶€ í´ë˜ìŠ¤ì˜ ì¸ìŠ¤í„´ìŠ¤ ë©”ì„œë“œ ë‚´ì—ì„œ ë‚´ë¶€ í´ë˜ìŠ¤ ìƒì„±ìë¥¼ í˜¸ì¶œí•¨ìœ¼ë¡œì¨ ìë™ìœ¼ë¡œ ì„¤ì •ëœë‹¤.

ì™¸ë¶€ í´ë˜ìŠ¤ ì•ˆì—ì„œ ë‚´ë¶€ í´ë˜ìŠ¤ë¥¼ ìƒì„±í•˜ë©´ ì»´íŒŒì¼ëŸ¬ê°€ ìë™ìœ¼ë¡œ `this`ë¥¼ ë„˜ê²¨ì¤Œ


```java
class Outer {
    class Inner { }

    void createInner() {
        Inner i = new Inner(); // ì»´íŒŒì¼ëŸ¬ê°€ ìë™ìœ¼ë¡œ thisë¥¼ ë„˜ê¹€: new Outer.Inner(this)
    }
}
```

---

"It is possible, though rare, to establish the association manually using the expression enclosingInstance.new MemberClass(args)."

```java
Outer outer = new Outer();
Outer.Inner inner = outer.new Inner();  // ğŸ‘ˆ outerì™€ ì—°ê²°í•´ì„œ ìƒì„±
```

> ë“œë¬¼ê¸´ í•˜ì§€ë§Œ, `enclosingInstance.new MemberClass(args)` ë¬¸ë²•ì„ ì‚¬ìš©í•˜ì—¬ **ì§ì ‘ ìˆ˜ë™ìœ¼ë¡œ ì—°ê²°ì„ ì„¤ì •**í•˜ëŠ” ê²ƒë„ ê°€ëŠ¥í•˜ë‹¤.

    

java

CopyEdit

`Outer outer = new Outer(); Outer.Inner inner = outer.new Inner();  // ğŸ‘ˆ outerì™€ ì—°ê²°í•´ì„œ ìƒì„±`

- ìœ„ì²˜ëŸ¼ `.new` êµ¬ë¬¸ì„ ì¨ì•¼ ë‚´ë¶€ í´ë˜ìŠ¤ ìƒì„±ì´ ê°€ëŠ¥í•©ë‹ˆë‹¤.
    

---

### ğŸ“Œ 4. **"As you would expect, the association takes up space in the nonstatic member class instance and adds time to its construction."**

#### ğŸ” í•´ì„

> ì˜ˆìƒí•  ìˆ˜ ìˆë“¯ì´, ì´ ì—°ê²°(association)ì€ ë‚´ë¶€ í´ë˜ìŠ¤ ê°ì²´ ì•ˆì— ë©”ëª¨ë¦¬ë¥¼ ì°¨ì§€í•˜ë©°, ìƒì„± ì‹œê°„ë„ ë” ë“ ë‹¤.

#### ğŸ’¡ ì„¤ëª…

- ë‚´ë¶€ í´ë˜ìŠ¤ëŠ” ë‚´ë¶€ì ìœ¼ë¡œ **ì™¸ë¶€ ì¸ìŠ¤í„´ìŠ¤ë¥¼ ì°¸ì¡°í•˜ëŠ” í•„ë“œ**ë¥¼ ê°–ìŠµë‹ˆë‹¤. (ì»´íŒŒì¼ ì‹œ `Outer this$0;` ê°™ì€ í•„ë“œê°€ ìƒê¹ë‹ˆë‹¤.)
    
- ë”°ë¼ì„œ:
    
    - ë©”ëª¨ë¦¬: ë‚´ë¶€ ê°ì²´ë§ˆë‹¤ ì™¸ë¶€ ê°ì²´ í¬ì¸í„° í•˜ë‚˜ ì¶”ê°€ë¨
        
    - ì„±ëŠ¥: ìƒì„± ì‹œ ì™¸ë¶€ ì°¸ì¡°ë¥¼ ì„¤ì •í•´ì•¼ í•˜ë¯€ë¡œ ì•½ê°„ì˜ ì˜¤ë²„í—¤ë“œ ë°œìƒ
        


| ê°œë…           | ì„¤ëª…                                         |
| ------------ | ------------------------------------------ |
| ë‚´ë¶€ í´ë˜ìŠ¤ ìƒì„± ì‹œ  | ì™¸ë¶€ í´ë˜ìŠ¤ ì¸ìŠ¤í„´ìŠ¤ë¥¼ ë°˜ë“œì‹œ ì°¸ì¡°í•´ì•¼ í•¨                    |
| ì´ ì—°ê²°ì€ ë³€ê²½ ê°€ëŠ¥? | âŒ ìƒì„± ì‹œì ì— ê³ ì •ë¨                               |
| ì¼ë°˜ì ì¸ ìƒì„± ë°©ì‹   | ì™¸ë¶€ í´ë˜ìŠ¤ì˜ ì¸ìŠ¤í„´ìŠ¤ ë©”ì„œë“œ ë‚´ì—ì„œ `new Inner()`         |
| ìˆ˜ë™ ìƒì„± ë°©ì‹     | ì™¸ë¶€ì—ì„œ `outer.new Inner()`                   |
| ì„±ëŠ¥ ì˜í–¥        | ë©”ëª¨ë¦¬: ì™¸ë¶€ ì¸ìŠ¤í„´ìŠ¤ ì°¸ì¡° í•„ë“œ í¬í•¨  <br>ì‹œê°„: ì—°ê²° ì„¤ì • ë¹„ìš© ë°œìƒ |

---

## ğŸ”š ê²°ë¡ 

> `non-static inner class`ëŠ” í•­ìƒ ì™¸ë¶€ ì¸ìŠ¤í„´ìŠ¤ì— ì¢…ì†ì ì´ë©°, ê·¸ ì—°ê²°ì€ ë©”ëª¨ë¦¬ì™€ ìƒì„± ì‹œê°„ì— ë¶€ë‹´ì„ ì¤„ ìˆ˜ ìˆìŠµë‹ˆë‹¤.  
> ê·¸ë˜ì„œ ì™¸ë¶€ ì¸ìŠ¤í„´ìŠ¤ê°€ ê¼­ í•„ìš”í•˜ì§€ ì•Šë‹¤ë©´ `static nested class`ë¥¼ ì“°ëŠ” ê²Œ ë” ë‚«ë‹¤ê³  Effective JavaëŠ” ë§í•˜ê³  ìˆëŠ” ê²ƒì…ë‹ˆë‹¤.


--------

```java
// Outer.java
public class Outer {
    private String msg = "hello";

    // static nested class
    public static class StaticNested {
        public void print() {
            System.out.println("StaticNested");
        }
    }

    // non-static inner class
    public class Inner {
        public void print() {
            System.out.println("Inner: " + msg);
        }
    }
}
```

```
â— javac Outer.java
â— ls | grep Outer2

// output
Outer2.class
Outer2.java
Outer2$Inner.class
Outer2$StaticNested.class

```


`javap -c Outer2$Inner` ì‹¤í–‰ ì‹œ

```java
Compiled from "Outer2.java"
public class Outer2 {
  public Outer2();
    Code:
         0: aload_0
         1: invokespecial #1                  // Method java/lang/Object."<init>":()V
         4: aload_0
         5: ldc           #7                  // String hello
         7: putfield      #9                  // Field msg:Ljava/lang/String;
        10: return

  public static void main(java.lang.String[]);
    Code:
         0: new           #15                 // class Outer2$StaticNested
         3: dup
         4: invokespecial #17                 // Method Outer2$StaticNested."<init>":()V
         7: invokevirtual #18                 // Method Outer2$StaticNested.print:()V
        10: new           #21                 // class Outer2$Inner
        13: dup
        14: new           #10                 // class Outer2
        17: dup
        18: invokespecial #23                 // Method "<init>":()V
        21: invokespecial #24                 // Method Outer2$Inner."<init>":(LOuter2;)V
        24: invokevirtual #27                 // Method Outer2$Inner.print:()V
        27: return
}
```

